tjdcs/__init__.py
tjdcs/clsInterface.py
tjdcs/clsPID.py
tjdcs/clsProcessSim.py
tjdcs/clsSFilter.py
tjdcs/clsSimulink.py
tjdcs/clsSimulinkOPCGateTask.py
tjdcs/clsSoftSensor.py
tjdcs/clsZFilter.py
tjdcs/funInterface.py
tjdcs/version.py
tjdcs/algorithm/MIMOSim2.cp312-win_amd64.pyd
tjdcs/algorithm/PIDalgorithm.cp312-win_amd64.pyd
tjdcs/algorithm/__init__.py
tjdcs/algorithm/tjAntiWindupLimter.cp312-win_amd64.pyd
tjdcs/algorithm/tjConstDetector.cp312-win_amd64.pyd
tjdcs/algorithm/tjDelay.cp312-win_amd64.pyd
tjdcs/algorithm/tjFilter.cp312-win_amd64.pyd
tjdcs/algorithm/tjLDLAG.cp312-win_amd64.pyd
tjdcs/algorithm/tjLPVPlant.cp312-win_amd64.pyd
tjdcs/algorithm/tjRateLimit.cp312-win_amd64.pyd
tjdcs/algorithm/tjSoftSensor.cp312-win_amd64.pyd
tjdcs/algorithm/tjTestSignal.cp312-win_amd64.pyd
tjdcs/algorithm/tjTrigger.cp312-win_amd64.pyd
tjdcs/algorithm/tjWatchDog.cp312-win_amd64.pyd
tjdcs/algorithm/tjcommon.cp312-win_amd64.pyd
tjdcs/algorithm/utilities.cp312-win_amd64.pyd
tjdcs-0.9.33.dist-info/METADATA
tjdcs-0.9.33.dist-info/WHEEL
tjdcs-0.9.33.dist-info/top_level.txt
tjdcs-0.9.33.dist-info/RECORD
