Metadata-Version: 2.4
Name: tjdcs
Version: 0.9.33
Summary: A control toolbox for online implimentation
Author-email: kkzhang <kkzhang3@hotmail.com>
Requires-Python: >=3.8
Requires-Dist: numpy
Requires-Dist: scipy
Requires-Dist: opcgatepy>=3.1
